python_openblas_build-0.3.28rc1.dist-info/LICENSE
python_openblas_build-0.3.28rc1.dist-info/METADATA
python_openblas_build-0.3.28rc1.dist-info/top_level.txt
python_openblas_build-0.3.28rc1.dist-info/RECORD
python_openblas_build-0.3.28rc1.dist-info/WHEEL
python_openblas_build/placeholder.cpython-36m-i386-linux-gnu.so
python_openblas_build/__init__.py
python_openblas_build/include/openblas/lapacke_config.h
python_openblas_build/include/openblas/lapacke_mangling.h
python_openblas_build/include/openblas/openblas_config.h
python_openblas_build/include/openblas/lapacke_utils.h
python_openblas_build/include/openblas/lapacke.h
python_openblas_build/include/openblas/f77blas.h
python_openblas_build/include/openblas/lapacke_example_aux.h
python_openblas_build/include/openblas/lapack.h
python_openblas_build/include/openblas/cblas.h
python_openblas_build/lib/libopenblas.a
python_openblas_build/lib/cmake/OpenBLAS/OpenBLASConfigVersion.cmake
python_openblas_build/lib/cmake/OpenBLAS/OpenBLASTargets.cmake
python_openblas_build/lib/cmake/OpenBLAS/OpenBLASConfig.cmake
python_openblas_build/lib/cmake/OpenBLAS/OpenBLASTargets-release.cmake
python_openblas_build/lib/pkgconfig/openblas.pc
