Metadata-Version: 2.1
Name: python_openblas_build
Version: 0.3.28rc1
Summary: Python packaging of OpenBLAS
Home-page: https://github.com/kbesrour-ma/python-openblas-build
Author: khaled-besrour
Author-email: khaledbesrour2@gmail.com
License: BSD 3-Clause
License-File: LICENSE
